[{"label": "class", "confidence": 0.9042977690696716, "topleft": {"x": 94, "y": 7}, "bottomright": {"x": 114, "y": 26}}, {"label": "class", "confidence": 0.9854534268379211, "topleft": {"x": 187, "y": 32}, "bottomright": {"x": 205, "y": 50}}, {"label": "class", "confidence": 0.7561262845993042, "topleft": {"x": 119, "y": 68}, "bottomright": {"x": 138, "y": 88}}, {"label": "class", "confidence": 0.9960862398147583, "topleft": {"x": 182, "y": 73}, "bottomright": {"x": 201, "y": 92}}, {"label": "class", "confidence": 0.9826924800872803, "topleft": {"x": 76, "y": 114}, "bottomright": {"x": 95, "y": 134}}]