[{"label": "class", "confidence": 0.854394257068634, "topleft": {"x": 52, "y": 1}, "bottomright": {"x": 62, "y": 12}}, {"label": "class", "confidence": 0.7170860171318054, "topleft": {"x": 64, "y": 0}, "bottomright": {"x": 76, "y": 8}}, {"label": "class", "confidence": 0.8200740218162537, "topleft": {"x": 132, "y": 0}, "bottomright": {"x": 143, "y": 6}}, {"label": "class", "confidence": 0.8089644908905029, "topleft": {"x": 169, "y": 0}, "bottomright": {"x": 179, "y": 10}}, {"label": "class", "confidence": 0.5967158675193787, "topleft": {"x": 15, "y": 17}, "bottomright": {"x": 24, "y": 29}}, {"label": "class", "confidence": 0.5106457471847534, "topleft": {"x": 133, "y": 37}, "bottomright": {"x": 143, "y": 49}}, {"label": "class", "confidence": 0.4760001599788666, "topleft": {"x": 90, "y": 55}, "bottomright": {"x": 100, "y": 67}}, {"label": "class", "confidence": 0.5757572650909424, "topleft": {"x": 106, "y": 48}, "bottomright": {"x": 118, "y": 61}}, {"label": "class", "confidence": 0.5033865571022034, "topleft": {"x": 155, "y": 49}, "bottomright": {"x": 165, "y": 61}}, {"label": "class", "confidence": 0.574941098690033, "topleft": {"x": 118, "y": 64}, "bottomright": {"x": 128, "y": 76}}, {"label": "class", "confidence": 0.7084276080131531, "topleft": {"x": 4, "y": 73}, "bottomright": {"x": 13, "y": 84}}, {"label": "class", "confidence": 0.6368135809898376, "topleft": {"x": 50, "y": 76}, "bottomright": {"x": 61, "y": 87}}, {"label": "class", "confidence": 0.6271966099739075, "topleft": {"x": 63, "y": 72}, "bottomright": {"x": 73, "y": 84}}, {"label": "class", "confidence": 0.514249861240387, "topleft": {"x": 83, "y": 69}, "bottomright": {"x": 94, "y": 81}}, {"label": "class", "confidence": 0.777622640132904, "topleft": {"x": 1, "y": 86}, "bottomright": {"x": 9, "y": 98}}, {"label": "class", "confidence": 0.635159432888031, "topleft": {"x": 179, "y": 80}, "bottomright": {"x": 189, "y": 93}}, {"label": "class", "confidence": 0.27420467138290405, "topleft": {"x": 5, "y": 92}, "bottomright": {"x": 12, "y": 103}}, {"label": "class", "confidence": 0.5262385606765747, "topleft": {"x": 102, "y": 95}, "bottomright": {"x": 114, "y": 108}}, {"label": "class", "confidence": 0.3818323314189911, "topleft": {"x": 171, "y": 92}, "bottomright": {"x": 180, "y": 103}}, {"label": "class", "confidence": 0.79167640209198, "topleft": {"x": 3, "y": 101}, "bottomright": {"x": 13, "y": 113}}, {"label": "class", "confidence": 0.43846696615219116, "topleft": {"x": 44, "y": 108}, "bottomright": {"x": 53, "y": 119}}, {"label": "class", "confidence": 0.6132108569145203, "topleft": {"x": 80, "y": 106}, "bottomright": {"x": 91, "y": 119}}, {"label": "class", "confidence": 0.6635512709617615, "topleft": {"x": 80, "y": 125}, "bottomright": {"x": 90, "y": 139}}, {"label": "class", "confidence": 0.5492857098579407, "topleft": {"x": 165, "y": 128}, "bottomright": {"x": 177, "y": 141}}, {"label": "class", "confidence": 0.39188265800476074, "topleft": {"x": 183, "y": 127}, "bottomright": {"x": 194, "y": 138}}, {"label": "class", "confidence": 0.5021458864212036, "topleft": {"x": 19, "y": 145}, "bottomright": {"x": 30, "y": 159}}, {"label": "class", "confidence": 0.53061842918396, "topleft": {"x": 67, "y": 143}, "bottomright": {"x": 77, "y": 155}}, {"label": "class", "confidence": 0.4747791290283203, "topleft": {"x": 120, "y": 148}, "bottomright": {"x": 129, "y": 159}}, {"label": "class", "confidence": 0.5720089077949524, "topleft": {"x": 145, "y": 149}, "bottomright": {"x": 154, "y": 160}}, {"label": "class", "confidence": 0.6607035398483276, "topleft": {"x": 88, "y": 152}, "bottomright": {"x": 97, "y": 166}}, {"label": "class", "confidence": 0.6115960478782654, "topleft": {"x": 78, "y": 163}, "bottomright": {"x": 88, "y": 176}}, {"label": "class", "confidence": 0.5280272364616394, "topleft": {"x": 85, "y": 167}, "bottomright": {"x": 97, "y": 179}}, {"label": "class", "confidence": 0.4636346101760864, "topleft": {"x": 89, "y": 171}, "bottomright": {"x": 101, "y": 181}}, {"label": "class", "confidence": 0.32357630133628845, "topleft": {"x": 122, "y": 163}, "bottomright": {"x": 133, "y": 174}}, {"label": "class", "confidence": 0.7277670502662659, "topleft": {"x": 0, "y": 178}, "bottomright": {"x": 8, "y": 190}}, {"label": "class", "confidence": 0.49996379017829895, "topleft": {"x": 14, "y": 191}, "bottomright": {"x": 23, "y": 199}}, {"label": "class", "confidence": 0.3995327353477478, "topleft": {"x": 154, "y": 187}, "bottomright": {"x": 164, "y": 198}}, {"label": "class", "confidence": 0.46529731154441833, "topleft": {"x": 184, "y": 186}, "bottomright": {"x": 193, "y": 195}}]