[{"label": "class", "confidence": 0.3819541037082672, "topleft": {"x": 3, "y": 0}, "bottomright": {"x": 8, "y": 6}}, {"label": "class", "confidence": 0.9230096936225891, "topleft": {"x": 12, "y": 3}, "bottomright": {"x": 18, "y": 10}}, {"label": "class", "confidence": 0.7383923530578613, "topleft": {"x": 45, "y": 0}, "bottomright": {"x": 50, "y": 5}}, {"label": "class", "confidence": 0.8915635943412781, "topleft": {"x": 57, "y": 2}, "bottomright": {"x": 64, "y": 10}}, {"label": "class", "confidence": 0.37494686245918274, "topleft": {"x": 55, "y": 1}, "bottomright": {"x": 62, "y": 9}}, {"label": "class", "confidence": 0.7443364858627319, "topleft": {"x": 63, "y": 0}, "bottomright": {"x": 69, "y": 6}}, {"label": "class", "confidence": 0.9380401968955994, "topleft": {"x": 89, "y": 5}, "bottomright": {"x": 95, "y": 12}}, {"label": "class", "confidence": 0.35287386178970337, "topleft": {"x": 122, "y": 2}, "bottomright": {"x": 128, "y": 7}}, {"label": "class", "confidence": 0.7008176445960999, "topleft": {"x": 124, "y": 3}, "bottomright": {"x": 130, "y": 10}}, {"label": "class", "confidence": 0.8638529777526855, "topleft": {"x": 138, "y": 3}, "bottomright": {"x": 143, "y": 10}}, {"label": "class", "confidence": 0.9362422227859497, "topleft": {"x": 152, "y": 0}, "bottomright": {"x": 159, "y": 7}}, {"label": "class", "confidence": 0.9101701974868774, "topleft": {"x": 163, "y": 3}, "bottomright": {"x": 170, "y": 11}}, {"label": "class", "confidence": 0.8425571918487549, "topleft": {"x": 172, "y": 2}, "bottomright": {"x": 178, "y": 10}}, {"label": "class", "confidence": 0.3618023097515106, "topleft": {"x": 168, "y": 1}, "bottomright": {"x": 176, "y": 11}}, {"label": "class", "confidence": 0.3537122905254364, "topleft": {"x": 0, "y": 14}, "bottomright": {"x": 5, "y": 20}}, {"label": "class", "confidence": 0.6297475695610046, "topleft": {"x": 23, "y": 10}, "bottomright": {"x": 28, "y": 18}}, {"label": "class", "confidence": 0.8376624584197998, "topleft": {"x": 19, "y": 14}, "bottomright": {"x": 27, "y": 22}}, {"label": "class", "confidence": 0.7848451733589172, "topleft": {"x": 105, "y": 11}, "bottomright": {"x": 112, "y": 20}}, {"label": "class", "confidence": 0.8620092868804932, "topleft": {"x": 115, "y": 15}, "bottomright": {"x": 122, "y": 23}}, {"label": "class", "confidence": 0.816600501537323, "topleft": {"x": 139, "y": 14}, "bottomright": {"x": 145, "y": 22}}, {"label": "class", "confidence": 0.35368067026138306, "topleft": {"x": 175, "y": 10}, "bottomright": {"x": 180, "y": 18}}, {"label": "class", "confidence": 0.7441612482070923, "topleft": {"x": 178, "y": 13}, "bottomright": {"x": 184, "y": 21}}, {"label": "class", "confidence": 0.9554511904716492, "topleft": {"x": 4, "y": 25}, "bottomright": {"x": 10, "y": 33}}, {"label": "class", "confidence": 0.8655996918678284, "topleft": {"x": 31, "y": 24}, "bottomright": {"x": 39, "y": 33}}, {"label": "class", "confidence": 0.3050765097141266, "topleft": {"x": 38, "y": 21}, "bottomright": {"x": 48, "y": 30}}, {"label": "class", "confidence": 0.7660607099533081, "topleft": {"x": 53, "y": 19}, "bottomright": {"x": 60, "y": 29}}, {"label": "class", "confidence": 0.5962962508201599, "topleft": {"x": 68, "y": 22}, "bottomright": {"x": 74, "y": 31}}, {"label": "class", "confidence": 0.5040832161903381, "topleft": {"x": 66, "y": 18}, "bottomright": {"x": 73, "y": 26}}, {"label": "class", "confidence": 0.6565462946891785, "topleft": {"x": 105, "y": 24}, "bottomright": {"x": 111, "y": 32}}, {"label": "class", "confidence": 0.6678385138511658, "topleft": {"x": 132, "y": 26}, "bottomright": {"x": 138, "y": 33}}, {"label": "class", "confidence": 0.5496376752853394, "topleft": {"x": 156, "y": 18}, "bottomright": {"x": 165, "y": 29}}, {"label": "class", "confidence": 0.7062680125236511, "topleft": {"x": 178, "y": 20}, "bottomright": {"x": 185, "y": 28}}, {"label": "class", "confidence": 0.8728421330451965, "topleft": {"x": 22, "y": 29}, "bottomright": {"x": 29, "y": 38}}, {"label": "class", "confidence": 0.45331892371177673, "topleft": {"x": 43, "y": 34}, "bottomright": {"x": 49, "y": 42}}, {"label": "class", "confidence": 0.7399178743362427, "topleft": {"x": 40, "y": 33}, "bottomright": {"x": 47, "y": 41}}, {"label": "class", "confidence": 0.43472957611083984, "topleft": {"x": 41, "y": 29}, "bottomright": {"x": 49, "y": 37}}, {"label": "class", "confidence": 0.8063384890556335, "topleft": {"x": 68, "y": 28}, "bottomright": {"x": 74, "y": 38}}, {"label": "class", "confidence": 0.7767122387886047, "topleft": {"x": 83, "y": 31}, "bottomright": {"x": 90, "y": 39}}, {"label": "class", "confidence": 0.4847143888473511, "topleft": {"x": 106, "y": 30}, "bottomright": {"x": 113, "y": 38}}, {"label": "class", "confidence": 0.7260036468505859, "topleft": {"x": 131, "y": 34}, "bottomright": {"x": 137, "y": 42}}, {"label": "class", "confidence": 0.5617630481719971, "topleft": {"x": 129, "y": 34}, "bottomright": {"x": 135, "y": 43}}, {"label": "class", "confidence": 0.4225665330886841, "topleft": {"x": 135, "y": 29}, "bottomright": {"x": 142, "y": 35}}, {"label": "class", "confidence": 0.6162760853767395, "topleft": {"x": 164, "y": 30}, "bottomright": {"x": 170, "y": 38}}, {"label": "class", "confidence": 0.656086266040802, "topleft": {"x": 165, "y": 33}, "bottomright": {"x": 173, "y": 43}}, {"label": "class", "confidence": 0.4983042776584625, "topleft": {"x": 167, "y": 29}, "bottomright": {"x": 174, "y": 37}}, {"label": "class", "confidence": 0.8103342056274414, "topleft": {"x": 179, "y": 31}, "bottomright": {"x": 185, "y": 39}}, {"label": "class", "confidence": 0.4023631811141968, "topleft": {"x": 195, "y": 36}, "bottomright": {"x": 199, "y": 43}}, {"label": "class", "confidence": 0.9389914870262146, "topleft": {"x": 4, "y": 45}, "bottomright": {"x": 10, "y": 53}}, {"label": "class", "confidence": 0.5921613574028015, "topleft": {"x": 17, "y": 41}, "bottomright": {"x": 22, "y": 49}}, {"label": "class", "confidence": 0.6520262956619263, "topleft": {"x": 38, "y": 45}, "bottomright": {"x": 44, "y": 53}}, {"label": "class", "confidence": 0.7516672611236572, "topleft": {"x": 46, "y": 41}, "bottomright": {"x": 52, "y": 49}}, {"label": "class", "confidence": 0.7204585075378418, "topleft": {"x": 40, "y": 44}, "bottomright": {"x": 47, "y": 51}}, {"label": "class", "confidence": 0.33886298537254333, "topleft": {"x": 50, "y": 42}, "bottomright": {"x": 53, "y": 47}}, {"label": "class", "confidence": 0.6698558926582336, "topleft": {"x": 79, "y": 42}, "bottomright": {"x": 85, "y": 51}}, {"label": "class", "confidence": 0.4096393883228302, "topleft": {"x": 78, "y": 40}, "bottomright": {"x": 84, "y": 47}}, {"label": "class", "confidence": 0.7670266628265381, "topleft": {"x": 116, "y": 44}, "bottomright": {"x": 122, "y": 52}}, {"label": "class", "confidence": 0.7591903805732727, "topleft": {"x": 131, "y": 45}, "bottomright": {"x": 136, "y": 53}}, {"label": "class", "confidence": 0.4148217737674713, "topleft": {"x": 132, "y": 43}, "bottomright": {"x": 138, "y": 50}}, {"label": "class", "confidence": 0.6266555190086365, "topleft": {"x": 137, "y": 43}, "bottomright": {"x": 143, "y": 51}}, {"label": "class", "confidence": 0.6678303480148315, "topleft": {"x": 135, "y": 41}, "bottomright": {"x": 141, "y": 50}}, {"label": "class", "confidence": 0.7588680982589722, "topleft": {"x": 151, "y": 45}, "bottomright": {"x": 157, "y": 53}}, {"label": "class", "confidence": 0.48899930715560913, "topleft": {"x": 150, "y": 40}, "bottomright": {"x": 156, "y": 47}}, {"label": "class", "confidence": 0.3152001202106476, "topleft": {"x": 154, "y": 43}, "bottomright": {"x": 159, "y": 51}}, {"label": "class", "confidence": 0.6966753602027893, "topleft": {"x": 172, "y": 43}, "bottomright": {"x": 179, "y": 50}}, {"label": "class", "confidence": 0.6607112884521484, "topleft": {"x": 168, "y": 40}, "bottomright": {"x": 176, "y": 49}}, {"label": "class", "confidence": 0.5490304827690125, "topleft": {"x": 195, "y": 42}, "bottomright": {"x": 199, "y": 49}}, {"label": "class", "confidence": 0.5226368308067322, "topleft": {"x": 0, "y": 55}, "bottomright": {"x": 5, "y": 62}}, {"label": "class", "confidence": 0.36575451493263245, "topleft": {"x": 0, "y": 56}, "bottomright": {"x": 2, "y": 66}}, {"label": "class", "confidence": 0.890354573726654, "topleft": {"x": 12, "y": 52}, "bottomright": {"x": 18, "y": 60}}, {"label": "class", "confidence": 0.7252535223960876, "topleft": {"x": 33, "y": 56}, "bottomright": {"x": 39, "y": 63}}, {"label": "class", "confidence": 0.6113703846931458, "topleft": {"x": 30, "y": 58}, "bottomright": {"x": 37, "y": 66}}, {"label": "class", "confidence": 0.7612907290458679, "topleft": {"x": 52, "y": 52}, "bottomright": {"x": 59, "y": 60}}, {"label": "class", "confidence": 0.770977258682251, "topleft": {"x": 79, "y": 55}, "bottomright": {"x": 85, "y": 63}}, {"label": "class", "confidence": 0.7687591910362244, "topleft": {"x": 98, "y": 55}, "bottomright": {"x": 104, "y": 63}}, {"label": "class", "confidence": 0.8162304759025574, "topleft": {"x": 141, "y": 56}, "bottomright": {"x": 147, "y": 63}}, {"label": "class", "confidence": 0.7371405363082886, "topleft": {"x": 138, "y": 57}, "bottomright": {"x": 144, "y": 65}}, {"label": "class", "confidence": 0.7498022317886353, "topleft": {"x": 150, "y": 51}, "bottomright": {"x": 157, "y": 59}}, {"label": "class", "confidence": 0.5198570489883423, "topleft": {"x": 146, "y": 50}, "bottomright": {"x": 153, "y": 60}}, {"label": "class", "confidence": 0.8150745630264282, "topleft": {"x": 174, "y": 51}, "bottomright": {"x": 180, "y": 59}}, {"label": "class", "confidence": 0.7673394680023193, "topleft": {"x": 196, "y": 56}, "bottomright": {"x": 199, "y": 64}}, {"label": "class", "confidence": 0.9532138109207153, "topleft": {"x": 2, "y": 66}, "bottomright": {"x": 8, "y": 74}}, {"label": "class", "confidence": 0.30705398321151733, "topleft": {"x": 1, "y": 66}, "bottomright": {"x": 3, "y": 74}}, {"label": "class", "confidence": 0.6552762389183044, "topleft": {"x": 29, "y": 62}, "bottomright": {"x": 36, "y": 71}}, {"label": "class", "confidence": 0.7026156187057495, "topleft": {"x": 47, "y": 67}, "bottomright": {"x": 53, "y": 75}}, {"label": "class", "confidence": 0.42412063479423523, "topleft": {"x": 45, "y": 68}, "bottomright": {"x": 51, "y": 75}}, {"label": "class", "confidence": 0.458549439907074, "topleft": {"x": 55, "y": 66}, "bottomright": {"x": 62, "y": 73}}, {"label": "class", "confidence": 0.5736027359962463, "topleft": {"x": 51, "y": 63}, "bottomright": {"x": 58, "y": 72}}, {"label": "class", "confidence": 0.3423614799976349, "topleft": {"x": 53, "y": 60}, "bottomright": {"x": 59, "y": 70}}, {"label": "class", "confidence": 0.793663740158081, "topleft": {"x": 121, "y": 65}, "bottomright": {"x": 127, "y": 72}}, {"label": "class", "confidence": 0.6223575472831726, "topleft": {"x": 130, "y": 62}, "bottomright": {"x": 136, "y": 69}}, {"label": "class", "confidence": 0.3565838932991028, "topleft": {"x": 126, "y": 62}, "bottomright": {"x": 132, "y": 70}}, {"label": "class", "confidence": 0.5307484269142151, "topleft": {"x": 129, "y": 61}, "bottomright": {"x": 134, "y": 67}}, {"label": "class", "confidence": 0.3201453983783722, "topleft": {"x": 133, "y": 63}, "bottomright": {"x": 137, "y": 68}}, {"label": "class", "confidence": 0.4739621579647064, "topleft": {"x": 136, "y": 61}, "bottomright": {"x": 143, "y": 69}}, {"label": "class", "confidence": 0.6906653046607971, "topleft": {"x": 157, "y": 65}, "bottomright": {"x": 164, "y": 73}}, {"label": "class", "confidence": 0.7935547232627869, "topleft": {"x": 174, "y": 67}, "bottomright": {"x": 180, "y": 75}}, {"label": "class", "confidence": 0.750400960445404, "topleft": {"x": 184, "y": 66}, "bottomright": {"x": 190, "y": 74}}, {"label": "class", "confidence": 0.3728650212287903, "topleft": {"x": 179, "y": 65}, "bottomright": {"x": 186, "y": 75}}, {"label": "class", "confidence": 0.4159592092037201, "topleft": {"x": 195, "y": 66}, "bottomright": {"x": 199, "y": 73}}, {"label": "class", "confidence": 0.8084768056869507, "topleft": {"x": 1, "y": 77}, "bottomright": {"x": 7, "y": 85}}, {"label": "class", "confidence": 0.7636024951934814, "topleft": {"x": 15, "y": 75}, "bottomright": {"x": 21, "y": 82}}, {"label": "class", "confidence": 0.7322970628738403, "topleft": {"x": 13, "y": 76}, "bottomright": {"x": 19, "y": 84}}, {"label": "class", "confidence": 0.8722366690635681, "topleft": {"x": 27, "y": 77}, "bottomright": {"x": 33, "y": 84}}, {"label": "class", "confidence": 0.34750890731811523, "topleft": {"x": 29, "y": 75}, "bottomright": {"x": 32, "y": 80}}, {"label": "class", "confidence": 0.5262969732284546, "topleft": {"x": 41, "y": 71}, "bottomright": {"x": 48, "y": 80}}, {"label": "class", "confidence": 0.5608037710189819, "topleft": {"x": 40, "y": 74}, "bottomright": {"x": 45, "y": 81}}, {"label": "class", "confidence": 0.5269860625267029, "topleft": {"x": 59, "y": 71}, "bottomright": {"x": 65, "y": 79}}, {"label": "class", "confidence": 0.6853882670402527, "topleft": {"x": 93, "y": 77}, "bottomright": {"x": 100, "y": 86}}, {"label": "class", "confidence": 0.8715596199035645, "topleft": {"x": 130, "y": 72}, "bottomright": {"x": 137, "y": 80}}, {"label": "class", "confidence": 0.5593632459640503, "topleft": {"x": 152, "y": 78}, "bottomright": {"x": 158, "y": 86}}, {"label": "class", "confidence": 0.8628676533699036, "topleft": {"x": 157, "y": 76}, "bottomright": {"x": 164, "y": 84}}, {"label": "class", "confidence": 0.3463978171348572, "topleft": {"x": 157, "y": 72}, "bottomright": {"x": 163, "y": 81}}, {"label": "class", "confidence": 0.6964501738548279, "topleft": {"x": 195, "y": 74}, "bottomright": {"x": 199, "y": 82}}, {"label": "class", "confidence": 0.9344474077224731, "topleft": {"x": 2, "y": 86}, "bottomright": {"x": 7, "y": 93}}, {"label": "class", "confidence": 0.31367000937461853, "topleft": {"x": 0, "y": 87}, "bottomright": {"x": 3, "y": 96}}, {"label": "class", "confidence": 0.8950871825218201, "topleft": {"x": 16, "y": 81}, "bottomright": {"x": 21, "y": 89}}, {"label": "class", "confidence": 0.35827675461769104, "topleft": {"x": 13, "y": 81}, "bottomright": {"x": 18, "y": 90}}, {"label": "class", "confidence": 0.8135681748390198, "topleft": {"x": 27, "y": 89}, "bottomright": {"x": 33, "y": 97}}, {"label": "class", "confidence": 0.31339314579963684, "topleft": {"x": 25, "y": 86}, "bottomright": {"x": 31, "y": 94}}, {"label": "class", "confidence": 0.8255708813667297, "topleft": {"x": 37, "y": 87}, "bottomright": {"x": 42, "y": 94}}, {"label": "class", "confidence": 0.4404800236225128, "topleft": {"x": 31, "y": 86}, "bottomright": {"x": 39, "y": 95}}, {"label": "class", "confidence": 0.41322389245033264, "topleft": {"x": 38, "y": 84}, "bottomright": {"x": 43, "y": 91}}, {"label": "class", "confidence": 0.6278433203697205, "topleft": {"x": 100, "y": 86}, "bottomright": {"x": 106, "y": 94}}, {"label": "class", "confidence": 0.37844181060791016, "topleft": {"x": 97, "y": 83}, "bottomright": {"x": 103, "y": 92}}, {"label": "class", "confidence": 0.5127696394920349, "topleft": {"x": 102, "y": 84}, "bottomright": {"x": 108, "y": 93}}, {"label": "class", "confidence": 0.6148631572723389, "topleft": {"x": 0, "y": 94}, "bottomright": {"x": 5, "y": 101}}, {"label": "class", "confidence": 0.5819966793060303, "topleft": {"x": 26, "y": 92}, "bottomright": {"x": 33, "y": 99}}, {"label": "class", "confidence": 0.7674542665481567, "topleft": {"x": 37, "y": 99}, "bottomright": {"x": 43, "y": 106}}, {"label": "class", "confidence": 0.36797472834587097, "topleft": {"x": 34, "y": 96}, "bottomright": {"x": 41, "y": 103}}, {"label": "class", "confidence": 0.323128879070282, "topleft": {"x": 38, "y": 95}, "bottomright": {"x": 43, "y": 103}}, {"label": "class", "confidence": 0.796169102191925, "topleft": {"x": 108, "y": 100}, "bottomright": {"x": 115, "y": 107}}, {"label": "class", "confidence": 0.6395076513290405, "topleft": {"x": 156, "y": 92}, "bottomright": {"x": 164, "y": 101}}, {"label": "class", "confidence": 0.7369807362556458, "topleft": {"x": 195, "y": 98}, "bottomright": {"x": 199, "y": 106}}, {"label": "class", "confidence": 0.369692325592041, "topleft": {"x": 195, "y": 96}, "bottomright": {"x": 199, "y": 103}}, {"label": "class", "confidence": 0.9085173010826111, "topleft": {"x": 2, "y": 109}, "bottomright": {"x": 8, "y": 117}}, {"label": "class", "confidence": 0.7978508472442627, "topleft": {"x": 36, "y": 103}, "bottomright": {"x": 43, "y": 110}}, {"label": "class", "confidence": 0.8157936334609985, "topleft": {"x": 47, "y": 103}, "bottomright": {"x": 54, "y": 111}}, {"label": "class", "confidence": 0.3153345584869385, "topleft": {"x": 45, "y": 103}, "bottomright": {"x": 51, "y": 109}}, {"label": "class", "confidence": 0.8517019152641296, "topleft": {"x": 54, "y": 109}, "bottomright": {"x": 60, "y": 117}}, {"label": "class", "confidence": 0.8323811292648315, "topleft": {"x": 84, "y": 107}, "bottomright": {"x": 91, "y": 116}}, {"label": "class", "confidence": 0.6836535334587097, "topleft": {"x": 116, "y": 102}, "bottomright": {"x": 122, "y": 111}}, {"label": "class", "confidence": 0.7935136556625366, "topleft": {"x": 142, "y": 102}, "bottomright": {"x": 149, "y": 110}}, {"label": "class", "confidence": 0.8338527083396912, "topleft": {"x": 161, "y": 107}, "bottomright": {"x": 167, "y": 115}}, {"label": "class", "confidence": 0.42091768980026245, "topleft": {"x": 164, "y": 106}, "bottomright": {"x": 169, "y": 114}}, {"label": "class", "confidence": 0.3473290503025055, "topleft": {"x": 174, "y": 106}, "bottomright": {"x": 181, "y": 113}}, {"label": "class", "confidence": 0.6950687766075134, "topleft": {"x": 195, "y": 108}, "bottomright": {"x": 199, "y": 116}}, {"label": "class", "confidence": 0.3495292663574219, "topleft": {"x": 195, "y": 105}, "bottomright": {"x": 199, "y": 113}}, {"label": "class", "confidence": 0.769446849822998, "topleft": {"x": 26, "y": 120}, "bottomright": {"x": 32, "y": 127}}, {"label": "class", "confidence": 0.6828060746192932, "topleft": {"x": 91, "y": 120}, "bottomright": {"x": 100, "y": 128}}, {"label": "class", "confidence": 0.6914417743682861, "topleft": {"x": 131, "y": 119}, "bottomright": {"x": 137, "y": 127}}, {"label": "class", "confidence": 0.7257232069969177, "topleft": {"x": 128, "y": 117}, "bottomright": {"x": 134, "y": 124}}, {"label": "class", "confidence": 0.5291900634765625, "topleft": {"x": 170, "y": 119}, "bottomright": {"x": 177, "y": 127}}, {"label": "class", "confidence": 0.7682753205299377, "topleft": {"x": 167, "y": 118}, "bottomright": {"x": 174, "y": 128}}, {"label": "class", "confidence": 0.30282267928123474, "topleft": {"x": 174, "y": 117}, "bottomright": {"x": 180, "y": 125}}, {"label": "class", "confidence": 0.7885580658912659, "topleft": {"x": 182, "y": 120}, "bottomright": {"x": 189, "y": 128}}, {"label": "class", "confidence": 0.6033937335014343, "topleft": {"x": 179, "y": 117}, "bottomright": {"x": 187, "y": 126}}, {"label": "class", "confidence": 0.6629433631896973, "topleft": {"x": 31, "y": 125}, "bottomright": {"x": 38, "y": 133}}, {"label": "class", "confidence": 0.7060542702674866, "topleft": {"x": 65, "y": 128}, "bottomright": {"x": 71, "y": 136}}, {"label": "class", "confidence": 0.665276288986206, "topleft": {"x": 75, "y": 125}, "bottomright": {"x": 81, "y": 133}}, {"label": "class", "confidence": 0.7846769094467163, "topleft": {"x": 115, "y": 125}, "bottomright": {"x": 122, "y": 133}}, {"label": "class", "confidence": 0.7074323296546936, "topleft": {"x": 152, "y": 131}, "bottomright": {"x": 158, "y": 139}}, {"label": "class", "confidence": 0.4139476418495178, "topleft": {"x": 156, "y": 130}, "bottomright": {"x": 163, "y": 140}}, {"label": "class", "confidence": 0.6088482141494751, "topleft": {"x": 172, "y": 130}, "bottomright": {"x": 178, "y": 139}}, {"label": "class", "confidence": 0.73407381772995, "topleft": {"x": 168, "y": 128}, "bottomright": {"x": 175, "y": 136}}, {"label": "class", "confidence": 0.6035224795341492, "topleft": {"x": 179, "y": 128}, "bottomright": {"x": 185, "y": 137}}, {"label": "class", "confidence": 0.7762748003005981, "topleft": {"x": 176, "y": 130}, "bottomright": {"x": 183, "y": 140}}, {"label": "class", "confidence": 0.744436502456665, "topleft": {"x": 193, "y": 130}, "bottomright": {"x": 199, "y": 137}}, {"label": "class", "confidence": 0.3763473927974701, "topleft": {"x": 192, "y": 128}, "bottomright": {"x": 199, "y": 137}}, {"label": "class", "confidence": 0.8698323965072632, "topleft": {"x": 12, "y": 135}, "bottomright": {"x": 18, "y": 142}}, {"label": "class", "confidence": 0.6647871732711792, "topleft": {"x": 33, "y": 139}, "bottomright": {"x": 39, "y": 147}}, {"label": "class", "confidence": 0.7067606449127197, "topleft": {"x": 30, "y": 141}, "bottomright": {"x": 38, "y": 149}}, {"label": "class", "confidence": 0.33614131808280945, "topleft": {"x": 36, "y": 137}, "bottomright": {"x": 43, "y": 147}}, {"label": "class", "confidence": 0.6355704665184021, "topleft": {"x": 43, "y": 139}, "bottomright": {"x": 50, "y": 148}}, {"label": "class", "confidence": 0.7364790439605713, "topleft": {"x": 41, "y": 141}, "bottomright": {"x": 48, "y": 149}}, {"label": "class", "confidence": 0.32670748233795166, "topleft": {"x": 56, "y": 139}, "bottomright": {"x": 63, "y": 147}}, {"label": "class", "confidence": 0.4268976151943207, "topleft": {"x": 51, "y": 134}, "bottomright": {"x": 60, "y": 144}}, {"label": "class", "confidence": 0.5933192372322083, "topleft": {"x": 60, "y": 141}, "bottomright": {"x": 67, "y": 149}}, {"label": "class", "confidence": 0.5379665493965149, "topleft": {"x": 84, "y": 137}, "bottomright": {"x": 90, "y": 145}}, {"label": "class", "confidence": 0.756773829460144, "topleft": {"x": 82, "y": 136}, "bottomright": {"x": 88, "y": 144}}, {"label": "class", "confidence": 0.3933861553668976, "topleft": {"x": 95, "y": 139}, "bottomright": {"x": 102, "y": 148}}, {"label": "class", "confidence": 0.7246072888374329, "topleft": {"x": 92, "y": 142}, "bottomright": {"x": 100, "y": 149}}, {"label": "class", "confidence": 0.46361878514289856, "topleft": {"x": 107, "y": 136}, "bottomright": {"x": 114, "y": 144}}, {"label": "class", "confidence": 0.564460813999176, "topleft": {"x": 106, "y": 133}, "bottomright": {"x": 112, "y": 142}}, {"label": "class", "confidence": 0.6768594980239868, "topleft": {"x": 115, "y": 140}, "bottomright": {"x": 121, "y": 148}}, {"label": "class", "confidence": 0.8911733031272888, "topleft": {"x": 162, "y": 141}, "bottomright": {"x": 168, "y": 149}}, {"label": "class", "confidence": 0.6793116927146912, "topleft": {"x": 160, "y": 138}, "bottomright": {"x": 167, "y": 146}}, {"label": "class", "confidence": 0.40113332867622375, "topleft": {"x": 174, "y": 135}, "bottomright": {"x": 180, "y": 142}}, {"label": "class", "confidence": 0.3465471565723419, "topleft": {"x": 190, "y": 141}, "bottomright": {"x": 197, "y": 149}}, {"label": "class", "confidence": 0.8628215193748474, "topleft": {"x": 0, "y": 147}, "bottomright": {"x": 5, "y": 155}}, {"label": "class", "confidence": 0.3777504861354828, "topleft": {"x": 0, "y": 149}, "bottomright": {"x": 2, "y": 157}}, {"label": "class", "confidence": 0.3050948679447174, "topleft": {"x": 1, "y": 148}, "bottomright": {"x": 2, "y": 154}}, {"label": "class", "confidence": 0.8861856460571289, "topleft": {"x": 16, "y": 152}, "bottomright": {"x": 22, "y": 159}}, {"label": "class", "confidence": 0.6923754811286926, "topleft": {"x": 31, "y": 148}, "bottomright": {"x": 37, "y": 157}}, {"label": "class", "confidence": 0.3759115934371948, "topleft": {"x": 31, "y": 145}, "bottomright": {"x": 36, "y": 152}}, {"label": "class", "confidence": 0.7676997780799866, "topleft": {"x": 83, "y": 149}, "bottomright": {"x": 90, "y": 157}}, {"label": "class", "confidence": 0.7592414021492004, "topleft": {"x": 132, "y": 153}, "bottomright": {"x": 138, "y": 160}}, {"label": "class", "confidence": 0.7091981768608093, "topleft": {"x": 140, "y": 145}, "bottomright": {"x": 146, "y": 153}}, {"label": "class", "confidence": 0.39975985884666443, "topleft": {"x": 136, "y": 148}, "bottomright": {"x": 144, "y": 156}}, {"label": "class", "confidence": 0.6816007494926453, "topleft": {"x": 163, "y": 152}, "bottomright": {"x": 169, "y": 160}}, {"label": "class", "confidence": 0.7106971740722656, "topleft": {"x": 192, "y": 152}, "bottomright": {"x": 198, "y": 159}}, {"label": "class", "confidence": 0.7801589369773865, "topleft": {"x": 188, "y": 151}, "bottomright": {"x": 194, "y": 159}}, {"label": "class", "confidence": 0.3456331491470337, "topleft": {"x": 196, "y": 150}, "bottomright": {"x": 199, "y": 155}}, {"label": "class", "confidence": 0.8135051131248474, "topleft": {"x": 37, "y": 161}, "bottomright": {"x": 43, "y": 169}}, {"label": "class", "confidence": 0.5945525765419006, "topleft": {"x": 35, "y": 159}, "bottomright": {"x": 41, "y": 166}}, {"label": "class", "confidence": 0.3373302221298218, "topleft": {"x": 39, "y": 160}, "bottomright": {"x": 42, "y": 166}}, {"label": "class", "confidence": 0.8047209978103638, "topleft": {"x": 52, "y": 156}, "bottomright": {"x": 59, "y": 165}}, {"label": "class", "confidence": 0.8698931932449341, "topleft": {"x": 88, "y": 162}, "bottomright": {"x": 94, "y": 170}}, {"label": "class", "confidence": 0.5857753157615662, "topleft": {"x": 84, "y": 157}, "bottomright": {"x": 91, "y": 167}}, {"label": "class", "confidence": 0.7330335378646851, "topleft": {"x": 111, "y": 156}, "bottomright": {"x": 117, "y": 164}}, {"label": "class", "confidence": 0.3665522336959839, "topleft": {"x": 109, "y": 157}, "bottomright": {"x": 115, "y": 165}}, {"label": "class", "confidence": 0.7919180393218994, "topleft": {"x": 116, "y": 158}, "bottomright": {"x": 123, "y": 166}}, {"label": "class", "confidence": 0.7864561676979065, "topleft": {"x": 133, "y": 161}, "bottomright": {"x": 138, "y": 169}}, {"label": "class", "confidence": 0.3522830605506897, "topleft": {"x": 131, "y": 159}, "bottomright": {"x": 137, "y": 168}}, {"label": "class", "confidence": 0.6974286437034607, "topleft": {"x": 166, "y": 156}, "bottomright": {"x": 172, "y": 163}}, {"label": "class", "confidence": 0.3766312897205353, "topleft": {"x": 194, "y": 156}, "bottomright": {"x": 199, "y": 164}}, {"label": "class", "confidence": 0.40827786922454834, "topleft": {"x": 5, "y": 171}, "bottomright": {"x": 10, "y": 178}}, {"label": "class", "confidence": 0.3699994683265686, "topleft": {"x": 8, "y": 172}, "bottomright": {"x": 14, "y": 180}}, {"label": "class", "confidence": 0.7904512286186218, "topleft": {"x": 46, "y": 166}, "bottomright": {"x": 52, "y": 174}}, {"label": "class", "confidence": 0.8117275238037109, "topleft": {"x": 64, "y": 171}, "bottomright": {"x": 71, "y": 179}}, {"label": "class", "confidence": 0.7740581631660461, "topleft": {"x": 84, "y": 171}, "bottomright": {"x": 91, "y": 178}}, {"label": "class", "confidence": 0.596176266670227, "topleft": {"x": 1, "y": 180}, "bottomright": {"x": 5, "y": 187}}, {"label": "class", "confidence": 0.3687191903591156, "topleft": {"x": 0, "y": 180}, "bottomright": {"x": 2, "y": 191}}, {"label": "class", "confidence": 0.8322604894638062, "topleft": {"x": 16, "y": 177}, "bottomright": {"x": 22, "y": 185}}, {"label": "class", "confidence": 0.427468478679657, "topleft": {"x": 13, "y": 177}, "bottomright": {"x": 19, "y": 186}}, {"label": "class", "confidence": 0.7472304701805115, "topleft": {"x": 52, "y": 181}, "bottomright": {"x": 58, "y": 189}}, {"label": "class", "confidence": 0.49819159507751465, "topleft": {"x": 52, "y": 177}, "bottomright": {"x": 57, "y": 185}}, {"label": "class", "confidence": 0.7473454475402832, "topleft": {"x": 100, "y": 181}, "bottomright": {"x": 107, "y": 188}}, {"label": "class", "confidence": 0.6255261898040771, "topleft": {"x": 107, "y": 183}, "bottomright": {"x": 113, "y": 191}}, {"label": "class", "confidence": 0.3663540184497833, "topleft": {"x": 103, "y": 182}, "bottomright": {"x": 111, "y": 191}}, {"label": "class", "confidence": 0.40671777725219727, "topleft": {"x": 168, "y": 182}, "bottomright": {"x": 175, "y": 190}}, {"label": "class", "confidence": 0.4984357953071594, "topleft": {"x": 166, "y": 184}, "bottomright": {"x": 173, "y": 192}}, {"label": "class", "confidence": 0.7166087627410889, "topleft": {"x": 184, "y": 183}, "bottomright": {"x": 190, "y": 190}}, {"label": "class", "confidence": 0.6713202595710754, "topleft": {"x": 193, "y": 183}, "bottomright": {"x": 198, "y": 190}}, {"label": "class", "confidence": 0.586179792881012, "topleft": {"x": 189, "y": 182}, "bottomright": {"x": 196, "y": 191}}, {"label": "class", "confidence": 0.8813859224319458, "topleft": {"x": 3, "y": 193}, "bottomright": {"x": 9, "y": 199}}, {"label": "class", "confidence": 0.4454084038734436, "topleft": {"x": 1, "y": 191}, "bottomright": {"x": 5, "y": 199}}, {"label": "class", "confidence": 0.34154900908470154, "topleft": {"x": 47, "y": 194}, "bottomright": {"x": 53, "y": 199}}, {"label": "class", "confidence": 0.7570432424545288, "topleft": {"x": 58, "y": 193}, "bottomright": {"x": 64, "y": 199}}, {"label": "class", "confidence": 0.40883639454841614, "topleft": {"x": 54, "y": 191}, "bottomright": {"x": 60, "y": 199}}, {"label": "class", "confidence": 0.336728572845459, "topleft": {"x": 63, "y": 193}, "bottomright": {"x": 69, "y": 199}}, {"label": "class", "confidence": 0.4544552266597748, "topleft": {"x": 77, "y": 192}, "bottomright": {"x": 83, "y": 199}}, {"label": "class", "confidence": 0.38402754068374634, "topleft": {"x": 85, "y": 193}, "bottomright": {"x": 91, "y": 199}}, {"label": "class", "confidence": 0.6789553761482239, "topleft": {"x": 81, "y": 192}, "bottomright": {"x": 88, "y": 199}}, {"label": "class", "confidence": 0.8113176822662354, "topleft": {"x": 94, "y": 194}, "bottomright": {"x": 102, "y": 199}}, {"label": "class", "confidence": 0.6268125772476196, "topleft": {"x": 107, "y": 188}, "bottomright": {"x": 113, "y": 195}}, {"label": "class", "confidence": 0.7594713568687439, "topleft": {"x": 130, "y": 194}, "bottomright": {"x": 136, "y": 199}}, {"label": "class", "confidence": 0.6092413067817688, "topleft": {"x": 136, "y": 189}, "bottomright": {"x": 143, "y": 196}}, {"label": "class", "confidence": 0.30923110246658325, "topleft": {"x": 152, "y": 194}, "bottomright": {"x": 158, "y": 199}}, {"label": "class", "confidence": 0.7467250823974609, "topleft": {"x": 171, "y": 193}, "bottomright": {"x": 177, "y": 199}}, {"label": "class", "confidence": 0.3922581374645233, "topleft": {"x": 167, "y": 190}, "bottomright": {"x": 177, "y": 199}}, {"label": "class", "confidence": 0.5764211416244507, "topleft": {"x": 191, "y": 193}, "bottomright": {"x": 196, "y": 199}}, {"label": "class", "confidence": 0.6579720973968506, "topleft": {"x": 188, "y": 192}, "bottomright": {"x": 195, "y": 199}}]